<?xml version="1.0" encoding="UTF-8"?>
<Configuration status="WARN">
    <Properties>
        <Property name="LOG_PATTERN">%d{yyyy-MM-dd HH:mm:ss.SSS} [%thread] %-5level %logger{36} - %msg%n</Property>
        <Property name="LOG_DIR">./logs</Property>
    </Properties>
    
    <Appenders>
        <!-- Console Appender -->
        <Console name="Console" target="SYSTEM_OUT">
            <PatternLayout pattern="${LOG_PATTERN}"/>
        </Console>
        
        <!-- File Appender for Application Logs -->
        <RollingFile name="ApplicationFile" fileName="${LOG_DIR}/application.log"
                     filePattern="${LOG_DIR}/application-%d{yyyy-MM-dd}-%i.log.gz">
            <PatternLayout pattern="${LOG_PATTERN}"/>
            <Policies>
                <TimeBasedTriggeringPolicy interval="1" modulate="true"/>
                <SizeBasedTriggeringPolicy size="10MB"/>
            </Policies>
            <DefaultRolloverStrategy max="30"/>
        </RollingFile>
        
        <!-- File Appender for Error Logs -->
        <RollingFile name="ErrorFile" fileName="${LOG_DIR}/error.log"
                     filePattern="${LOG_DIR}/error-%d{yyyy-MM-dd}-%i.log.gz">
            <PatternLayout pattern="${LOG_PATTERN}"/>
            <Policies>
                <TimeBasedTriggeringPolicy interval="1" modulate="true"/>
                <SizeBasedTriggeringPolicy size="5MB"/>
            </Policies>
            <DefaultRolloverStrategy max="30"/>
            <Filters>
                <ThresholdFilter level="ERROR" onMatch="ACCEPT" onMismatch="DENY"/>
            </Filters>
        </RollingFile>
        
        <!-- File Appender for Audit Logs -->
        <RollingFile name="AuditFile" fileName="${LOG_DIR}/audit.log"
                     filePattern="${LOG_DIR}/audit-%d{yyyy-MM-dd}-%i.log.gz">
            <PatternLayout pattern="${LOG_PATTERN}"/>
            <Policies>
                <TimeBasedTriggeringPolicy interval="1" modulate="true"/>
                <SizeBasedTriggeringPolicy size="10MB"/>
            </Policies>
            <DefaultRolloverStrategy max="60"/>
        </RollingFile>
    </Appenders>
    
    <Loggers>
        <!-- Application specific logger -->
        <Logger name="com.example.legacyapp" level="DEBUG" additivity="false">
            <AppenderRef ref="Console"/>
            <AppenderRef ref="ApplicationFile"/>
            <AppenderRef ref="ErrorFile"/>
        </Logger>
        
        <!-- Audit logger -->
        <Logger name="com.example.legacyapp.audit" level="INFO" additivity="false">
            <AppenderRef ref="AuditFile"/>
            <AppenderRef ref="Console"/>
        </Logger>
        
        <!-- Spring Framework logger -->
        <Logger name="org.springframework" level="INFO" additivity="false">
            <AppenderRef ref="Console"/>
            <AppenderRef ref="ApplicationFile"/>
        </Logger>
        
        <!-- Hibernate logger -->
        <Logger name="org.hibernate" level="WARN" additivity="false">
            <AppenderRef ref="Console"/>
            <AppenderRef ref="ApplicationFile"/>
        </Logger>
        
        <!-- Root Logger -->
        <Root level="INFO">
            <AppenderRef ref="Console"/>
            <AppenderRef ref="ApplicationFile"/>
            <AppenderRef ref="ErrorFile"/>
        </Root>
    </Loggers>
</Configuration>